jigeumseoul/__init__.py
jigeumseoul/seoul.py
jigeumseoul-0.1.0.dist-info/METADATA
jigeumseoul-0.1.0.dist-info/WHEEL
jigeumseoul-0.1.0.dist-info/top_level.txt
jigeumseoul-0.1.0.dist-info/RECORD
