Metadata-Version: 2.1
Name: jigeumseoul
Version: 0.1.0
Summary: Default template for PDM package
Author-email: Seokxkyu <kyuseok000@gmail.com>
License: MIT
Requires-Python: >=3.9
Requires-Dist: pytz>=2024.2
